{
    "match": {
        "getAll": "Matches retrieved",
        "getOne": "Match retrieved",
        "userMatches": "User matches retrieved",
        "matchDeleted": "Match deleted",
        "inviteSent": "Invite sent",
        "userAlreadyInvited": "User already invited",
        "userAlreadyInMatch": "User already in match",
        "inviteAccepted": "Invite accepted",
        "userNotInvited": "User not invited",
        "inviteDeclined": "Invite declined",
        "joinPublicMatch": "Joined public match",
        "matchNotPublic": "Match not public",
        "matchLimitExceeded": "Match limit exceeded",
        "matchNotFound": "No match found for this id",
        "matchCreated": "The match was successfully created",
        "badStatusUpdate": "The new status should be a valid value"
    },

    "defaults" : {
        "badRequest": "Bad Request",
        "serverError": "Internal Server Error",
        "invalidParams": "Invalid parameters"
    }
}